deeru_qiniu/__init__.py
deeru_qiniu/apps.py
deeru_qiniu/consts.py
deeru_qiniu/qiniu_manager.py
deeru_qiniu/signals.py
deeru_qiniu/management/__init__.py
deeru_qiniu/management/commands/__init__.py
deeru_qiniu/management/commands/delete_qiniu.py
deeru_qiniu/management/commands/init_qiniu.py
deeru_qiniu/management/commands/upload_qiniu.py
deeru_qiniu/migrations/__init__.py
deeru_qiniu-1.0.0.dist-info/METADATA
deeru_qiniu-1.0.0.dist-info/RECORD
deeru_qiniu-1.0.0.dist-info/WHEEL
deeru_qiniu-1.0.0.dist-info/top_level.txt
